sungram/__init__.py
sungram/base.py
sungram/bot.py
sungram/client.py
sungram-0.1.dist-info/LICENSE
sungram-0.1.dist-info/METADATA
sungram-0.1.dist-info/WHEEL
sungram-0.1.dist-info/top_level.txt
sungram-0.1.dist-info/RECORD
